dlmr_tools/__init__.py
dlmr_tools/version.py
dlmr_tools/client/__init__.py
dlmr_tools/client/client.py
dlmr_tools/client/templates/template.py
dlmr_tools/data_tool/__init__.py
dlmr_tools/data_tool/data.py
dlmr_tools/data_tool/list.py
dlmr_tools/graph_tool/__init__.py
dlmr_tools/graph_tool/graph_1D.py
dlmr_tools/graph_tool/graph_2D.py
dlmr_tools/graph_tool/graph_3D.py
dlmr_tools-0.1.4.dist-info/METADATA
dlmr_tools-0.1.4.dist-info/WHEEL
dlmr_tools-0.1.4.dist-info/entry_points.txt
dlmr_tools-0.1.4.dist-info/licenses/LICENSE.md
dlmr_tools-0.1.4.dist-info/RECORD
