Metadata-Version: 2.3
Name: dlmr_tools
Version: 0.1.4
Summary: Tool to extract data from xlsx files and create graphs
Project-URL: Source code, https://github.com/yanis-dlmr/dlmr_tools
Author-email: Yanis Delamare <yanisdeladraw@gmail.com>
License-Expression: MIT
License-File: LICENSE.md
Classifier: License :: OSI Approved :: MIT License
Classifier: Operating System :: OS Independent
Classifier: Programming Language :: Python :: 3
Requires-Python: >=3.8
Requires-Dist: matplotlib>=3.9.2
Requires-Dist: numpy>=2.1.1
Requires-Dist: pandas>=2.2.3
